heterodyne_postprocessing/EvaluatePostProcessing.py
heterodyne_postprocessing/__init__.py
heterodyne_postprocessing/configurations/__init__.py
heterodyne_postprocessing/configurations/configuration.py
heterodyne_postprocessing/configurations/configurationprocessed.py
heterodyne_postprocessing/misc/__init__.py
heterodyne_postprocessing/misc/hdf5Class.py
heterodyne_postprocessing/processing/__init__.py
heterodyne_postprocessing/processing/postProcessor.py
heterodyne_postprocessing/processing/postProcessorAvg.py
heterodyne_postprocessing/processing/postProcessorCSVSaver.py
heterodyne_postprocessing/processing/postProcessorCalibration.py
heterodyne_postprocessing/processing/postProcessorConfigurationMethods.py
heterodyne_postprocessing/processing/postProcessorHDF5.py
heterodyne_postprocessing/processing/postProcessorPlotSpectra.py
heterodyne_postprocessing/processing/postProcessorPlotTransients.py
heterodyne_postprocessing/processing/postProcessorPlottingUtilities.py
heterodyne_postprocessing/processing/postProcessorTimeResolved.py
heterodyne_postprocessing/utilities/IRis-Lens.py
heterodyne_postprocessing/utilities/renormalize_TR.py
heterodyne_postprocessing/utilities/unnormalize.py
orange_spectroscopy_prototypes-2025.8.14.dist-info/licenses/LICENSE
orangecontrib/protospec/__init__.py
orangecontrib/protospec/data.py
orangecontrib/protospec/datasets/PolyPropylene_FTIR_1100-1350.tab.gz
orangecontrib/protospec/datasets/irisf1_v7_0_0_processed_data.h5
orangecontrib/protospec/scripts/acquisition_average.py
orangecontrib/protospec/scripts/add_lag_measurement.py
orangecontrib/protospec/scripts/energy_calibration.py
orangecontrib/protospec/scripts/matlab_to_spec_table.py
orangecontrib/protospec/scripts/spectral_smoothing.py
orangecontrib/protospec/tests/__init__.py
orangecontrib/protospec/tests/test_io.py
orangecontrib/protospec/tests/test_irisf1_reader.py
orangecontrib/protospec/tutorials/IRis-F1_EnergyCalibration.ows
orangecontrib/protospec/tutorials/IRis-F1_Static.ows
orangecontrib/protospec/tutorials/IRis-F1_TimeResolved.ows
orange_spectroscopy_prototypes-2025.8.14.dist-info/METADATA
orange_spectroscopy_prototypes-2025.8.14.dist-info/WHEEL
orange_spectroscopy_prototypes-2025.8.14.dist-info/entry_points.txt
orange_spectroscopy_prototypes-2025.8.14.dist-info/top_level.txt
orange_spectroscopy_prototypes-2025.8.14.dist-info/RECORD
