Metadata-Version: 2.4
Name: orange-spectroscopy-prototypes
Version: 2025.8.14
Summary: Prototype widgets for orange-spectroscopy add-on
Author-email: Stuart Read <stuart.read@lightsource.ca>
Project-URL: Homepage, https://github.com/Quasars/orange-spectroscopy-prototypes
Project-URL: Issues, https://github.com/Quasars/orange-spectroscopy-prototypes/issues
Keywords: orange3 add-on,spectroscopy,prototypes
Classifier: Programming Language :: Python :: 3
Classifier: License :: OSI Approved :: GNU General Public License v3 or later (GPLv3+)
Classifier: Operating System :: OS Independent
Classifier: Development Status :: 3 - Alpha
Requires-Python: >=3.10
License-File: LICENSE
Requires-Dist: orange-spectroscopy>=0.8.1
Provides-Extra: doc
Requires-Dist: sphinx; extra == "doc"
Requires-Dist: recommonmark; extra == "doc"
Requires-Dist: sphinx_rtd_theme; extra == "doc"
Provides-Extra: test
Requires-Dist: pytest; extra == "test"
Requires-Dist: coverage; extra == "test"
Requires-Dist: flake8; extra == "test"
Requires-Dist: flake8-bugbear; extra == "test"
Requires-Dist: flake8-pyproject; extra == "test"
Requires-Dist: black; extra == "test"
Provides-Extra: dev
Requires-Dist: pre-commit; extra == "dev"
Dynamic: license-file
